LICENSE.txt
MANIFEST.in
README.rst
setup.py
pydmfet/__init__.py
pydmfet/version.py
pydmfet.egg-info/PKG-INFO
pydmfet.egg-info/SOURCES.txt
pydmfet.egg-info/dependency_links.txt
pydmfet.egg-info/not-zip-safe
pydmfet.egg-info/top_level.txt
pydmfet/dfet_ao/__init__.py
pydmfet/dfet_ao/dfet.py
pydmfet/dfet_ao/oep.py
pydmfet/dfet_ao/scf.py
pydmfet/dmet/__init__.py
pydmfet/dmet/dmet.py
pydmfet/libcpp/__init__.py
pydmfet/libcpp/fd_hess.py
pydmfet/libcpp/mkl_svd.py
pydmfet/libcpp/oep_hess.py
pydmfet/libcpp/test.py
pydmfet/libcpp/hess/hess.cpp
pydmfet/libcpp/linalg/fblas.h
pydmfet/libcpp/linalg/svd.cpp
pydmfet/libgen/__init__.py
pydmfet/libgen/ops.py
pydmfet/locints/__init__.py
pydmfet/locints/iao_helper.py
pydmfet/locints/localintegrals.py
pydmfet/locints/locints_base.py
pydmfet/locints/locints_wf.py
pydmfet/locints/mmn_wannier90.py
pydmfet/oep/__init__.py
pydmfet/oep/func_leastsq.py
pydmfet/oep/func_wuyang.py
pydmfet/oep/init_dens_par.py
pydmfet/oep/legacy.py
pydmfet/oep/oep_main.py
pydmfet/oep/oep_optimize.py
pydmfet/oep/oep_params.py
pydmfet/opt/__init__.py
pydmfet/opt/newton.py
pydmfet/proj_ao/__init__.py
pydmfet/proj_ao/proj_embed.py
pydmfet/qcwrap/__init__.py
pydmfet/qcwrap/fermi.py
pydmfet/qcwrap/pyscf_rhf.py
pydmfet/qcwrap/pyscf_rks.py
pydmfet/qcwrap/pyscf_rks_ao.py
pydmfet/qcwrap/pyscf_rks_nonscf.py
pydmfet/qcwrap/pyscf_rks_nonscf_ao.py
pydmfet/sdmfet/__init__.py
pydmfet/sdmfet/dmfet.py
pydmfet/subspac/__init__.py
pydmfet/subspac/buildsub.py
pydmfet/subspac/buildsub_2.py
pydmfet/tools/__init__.py
pydmfet/tools/misc.py
pydmfet/tools/printlib.py
pydmfet/tools/sym.py
pydmfet/tools/timelib.py
pydmfet/tools/umat.py
pydmfet/tools/vrlib.py