Metadata-Version: 1.2
Name: pydmfet
Version: 0.1.1
Summary: subspace DMFET
Home-page: https://github.com/fishjojo/pydmfet/pydmfet
Author: Xing Zhang
Author-email: xzhang8@caltech.edu
Maintainer: Xing Zhang
Maintainer-email: xzhang8@caltech.edu
License: BSD
Project-URL: Bug Tracker, https://github.com/fishjojo/pydmfet/issues
Project-URL: Source Code, https://github.com/fishjojo/pydmfet/pydmfet
Platform: Linux
Platform: Mac OS-X
Platform: Unix
Classifier: Development Status :: 5 - Production/Stable
Classifier: Intended Audience :: Science/Research
Classifier: License :: OSI Approved :: BSD License
Classifier: Programming Language :: C
Classifier: Programming Language :: Python
Classifier: Programming Language :: Python :: 3.5
Classifier: Programming Language :: Python :: 3.6
Classifier: Programming Language :: Python :: 3.7
Classifier: Topic :: Scientific/Engineering
Classifier: Operating System :: POSIX
Classifier: Operating System :: Unix
Classifier: Operating System :: MacOS
Requires-Python: >=3.5
